rodrigo_mercator_project_name/__init__.py
rodrigo_mercator_project_name-0.1.0.dist-info/METADATA
rodrigo_mercator_project_name-0.1.0.dist-info/WHEEL
rodrigo_mercator_project_name-0.1.0.dist-info/RECORD
