Metadata-Version: 2.1
Name: rodrigo-mercator-project-name
Version: 0.1.0
Summary: 
Author: MercatorAI
Author-email: team@mercator.ai
Requires-Python: >=3.13,<4.0
Classifier: Programming Language :: Python :: 3
Classifier: Programming Language :: Python :: 3.13
